src/__init__.py
src/api_client.py
src/cli.py
src/config.py
src/context.py
src/models.py
src/ui_controller.py
src/api/__init__.py
src/api/base.py
src/api/course.py
src/api/problem.py
src/api/problemset.py
src/api/submission.py
src/api/user.py
src/commands/__init__.py
src/commands/auth.py
src/commands/config.py
src/commands/course.py
src/commands/problem.py
src/commands/problemset.py
src/commands/submission.py
src/commands/user.py
termoj-0.1.2.dist-info/LICENSE
termoj-0.1.2.dist-info/METADATA
termoj-0.1.2.dist-info/WHEEL
termoj-0.1.2.dist-info/entry_points.txt
termoj-0.1.2.dist-info/top_level.txt
termoj-0.1.2.dist-info/RECORD
