Metadata-Version: 2.1
Name: termoj
Version: 0.1.2
Summary: A terminal cli tool for SJTU ACM-OJ platform. Built with click and rich.
Author-email: uke <uke_sjtu@sjtu.edu.cn>
License: MIT License
Requires-Python: <3.12,>=3.8
License-File: LICENSE
Requires-Dist: click>=8.0
Requires-Dist: rich>=13.0
Requires-Dist: pylatexenc>=2.10
Requires-Dist: requests>=2.0
Provides-Extra: dev
Requires-Dist: black~=24.3.0; extra == "dev"
Requires-Dist: isort~=5.12.0; extra == "dev"
Requires-Dist: pytest~=7.4.0; extra == "dev"
Requires-Dist: pytest-cov~=4.1.0; extra == "dev"
Requires-Dist: tox~=4.23.0; extra == "dev"
Requires-Dist: pydantic~=2.10.0; extra == "dev"
Requires-Dist: twine>=6.0.0; extra == "dev"
